{"unique_id": 3083875179, "base": -1, "derived": false, "words": [{"unique_id": 9484428885, "name": "soft", "children": [], "parent": 3083875179}, {"unique_id": 3188708137, "name": "hard", "children": [], "parent": 3083875179}, {"unique_id": 1758747026, "name": "smooth / sleek", "children": [], "parent": 3083875179}, {"unique_id": 1803532876, "name": "rough", "children": [], "parent": 3083875179}, {"unique_id": 6896425820, "name": "humid", "children": [], "parent": 3083875179}, {"unique_id": 2724059047, "name": "dry", "children": [], "parent": 3083875179}, {"unique_id": 8910043035, "name": "wet", "children": [], "parent": 3083875179}, {"unique_id": 1126049171, "name": "prickly", "children": [], "parent": 3083875179}, {"unique_id": 8358082832, "name": "frozen", "children": [], "parent": 3083875179}, {"unique_id": 5904847688, "name": "fluffy", "children": [], "parent": 3083875179}, {"unique_id": 2787948147, "name": "oily", "children": [], "parent": 3083875179}, {"unique_id": 6708015481, "name": "slimy", "children": [], "parent": 3083875179}, {"unique_id": 4565814875, "name": "hot", "children": [], "parent": 3083875179}, {"unique_id": 5817794145, "name": "cold", "children": [], "parent": 3083875179}, {"unique_id": 6214099461, "name": "muddy", "children": [], "parent": 3083875179}, {"unique_id": 8617335220, "name": "warm", "children": [], "parent": 3083875179}], "category": "Materials", "name": "Tactile Qualities"}