{"unique_id": 3583994492, "base": -1, "derived": false, "words": [{"unique_id": 2615424918, "name": "symbol", "children": [], "parent": 3583994492}, {"unique_id": 2389780614, "name": "signal", "children": [], "parent": 3583994492}, {"unique_id": 1719584158, "name": "leitmotif", "children": [], "parent": 3583994492}, {"unique_id": 6987396080, "name": "cultural convention", "children": [], "parent": 3583994492}, {"unique_id": 3129583591, "name": "stereotypes", "children": [], "parent": 3583994492}, {"unique_id": 5922342163, "name": "rhyme / isotopy", "children": [], "parent": 3583994492}, {"unique_id": 1612429084, "name": "genre conventions", "children": [], "parent": 3583994492}, {"unique_id": 8672659425, "name": "characterization", "children": [], "parent": 3583994492}, {"unique_id": 9381620777, "name": "character relationships", "children": [], "parent": 3583994492}, {"unique_id": 2688565738, "name": "milieu", "children": [], "parent": 3583994492}, {"unique_id": 6805631877, "name": "taste", "children": [], "parent": 3583994492}, {"unique_id": 1471060525, "name": "sociopolitical marker", "children": [], "parent": 3583994492}, {"unique_id": 4022084121, "name": "cultural contextualization", "children": [], "parent": 3583994492}, {"unique_id": 4056908042, "name": "race", "children": [], "parent": 3583994492}, {"unique_id": 2578398378, "name": "gender", "children": [], "parent": 3583994492}, {"unique_id": 6215968132, "name": "metaphor", "children": [], "parent": 3583994492}], "category": "Key Words", "name": "Higher Order Semantics"}