{"name": "Surfaces Objects", "uuid": "32d23a35-0f56-4074-aedf-48d9a6e41a4d", "category": "Materials", "unique_id": 4636180237, "words": [{"name": "opaque", "unique_id": 7783643387, "uuid": "a887dce1-7dcf-4345-9b54-2de6578a340e", "parent": 4636180237, "children": [], "organization_group": 0, "complexity_lvl": 0, "complexity_group": "", "image_urls": []}, {"name": "translucent", "unique_id": 3875011064, "uuid": "06f4705b-8822-4e34-83fd-3bb25cedf492", "parent": 4636180237, "children": [], "organization_group": 0, "complexity_lvl": 0, "complexity_group": "", "image_urls": []}, {"name": "transparent", "unique_id": 9546960216, "uuid": "014177fb-cca2-469e-900a-52422b518cd1", "parent": 4636180237, "children": [], "organization_group": 0, "complexity_lvl": 0, "complexity_group": "", "image_urls": []}, {"name": "glossy", "unique_id": 8371791556, "uuid": "f09d1607-91da-4079-ba7f-36230b588979", "parent": 4636180237, "children": [], "organization_group": 0, "complexity_lvl": 0, "complexity_group": "", "image_urls": []}, {"name": "semi glossy", "unique_id": 9426946634, "uuid": "342e8b13-1b2f-4816-b4f1-a6e47915283a", "parent": 4636180237, "children": [], "organization_group": 0, "complexity_lvl": 0, "complexity_group": "", "image_urls": []}, {"name": "shimmering", "unique_id": 5419298985, "uuid": "abc0eb57-1e46-41a5-ba4f-96be0b0853e7", "parent": 4636180237, "children": [], "organization_group": 0, "complexity_lvl": 0, "complexity_group": "", "image_urls": []}, {"name": "shiny", "unique_id": 2023830468, "uuid": "b2fa91c2-e206-415f-9633-947b0f417104", "parent": 4636180237, "children": [], "organization_group": 0, "complexity_lvl": 0, "complexity_group": "", "image_urls": []}, {"name": "iridescent", "unique_id": 9254448844, "uuid": "0e5605f4-e9b5-4658-b5d3-986bd680e101", "parent": 4636180237, "children": [], "organization_group": 0, "complexity_lvl": 0, "complexity_group": "", "image_urls": []}, {"name": "dull", "unique_id": 7351743502, "uuid": "9ad7b5c4-668a-4933-9a2c-af6c05ffe136", "parent": 4636180237, "children": [], "organization_group": 0, "complexity_lvl": 0, "complexity_group": "", "image_urls": []}, {"name": "rough", "unique_id": 2545849254, "uuid": "3639af40-03cb-4311-92fd-0524c7a3f22c", "parent": 4636180237, "children": [], "organization_group": 0, "complexity_lvl": 0, "complexity_group": "", "image_urls": []}, {"name": "glowing ", "unique_id": 9169656910, "uuid": "e6ebf6b8-702b-4e6f-b604-26d8cd8eaa08", "parent": 4636180237, "children": [], "organization_group": 0, "complexity_lvl": 0, "complexity_group": "", "image_urls": []}, {"name": "sparkling", "unique_id": 4426578817, "uuid": "a38fc4ef-a015-4bc5-bc25-cecab28ae5c0", "parent": 4636180237, "children": [], "organization_group": 0, "complexity_lvl": 0, "complexity_group": "", "image_urls": []}], "image_urls": []}